adebiet/__init__.py
adebiet/adebiet.py
adebiet-0.0.1.dist-info/METADATA
adebiet-0.0.1.dist-info/WHEEL
adebiet-0.0.1.dist-info/top_level.txt
adebiet-0.0.1.dist-info/RECORD
