Metadata-Version: 2.1
Name: adebiet
Version: 0.0.1
Summary: Adebiet
Home-page: https://github.com/andreihar/adebiet
Author: Andrei Harbachov
Author-email: andrei.harbachov@gmail.com
License: MIT
Keywords: python,kazakh,nlp
Classifier: Topic :: Text Processing :: Linguistic
Classifier: Development Status :: 1 - Planning
Classifier: Intended Audience :: Developers
Classifier: Programming Language :: Python :: 3
Classifier: Operating System :: Unix
Classifier: Operating System :: MacOS :: MacOS X
Classifier: Operating System :: Microsoft :: Windows
Requires-Python: >=3.8
